raganything/__init__.py
raganything/batch.py
raganything/batch_parser.py
raganything/config.py
raganything/enhanced_markdown.py
raganything/modalprocessors.py
raganything/parser.py
raganything/processor.py
raganything/prompt.py
raganything/query.py
raganything/raganything.py
raganything/utils.py
raganything-1.2.7.dist-info/licenses/LICENSE
raganything-1.2.7.dist-info/METADATA
raganything-1.2.7.dist-info/WHEEL
raganything-1.2.7.dist-info/top_level.txt
raganything-1.2.7.dist-info/RECORD
