Metadata-Version: 2.4
Name: raganything
Version: 1.2.7
Summary: RAGAnything: All-in-One RAG System
Home-page: https://github.com/HKUDS/RAG-Anything
Author: ZiruiGuo
Project-URL: Documentation, https://github.com/HKUDS/RAG-Anything
Project-URL: Source, https://github.com/HKUDS/RAG-Anything
Project-URL: Tracker, https://github.com/HKUDS/RAG-Anything/issues
Classifier: Development Status :: 4 - Beta
Classifier: Programming Language :: Python :: 3
Classifier: License :: OSI Approved :: MIT License
Classifier: Operating System :: OS Independent
Classifier: Intended Audience :: Developers
Classifier: Topic :: Software Development :: Libraries :: Python Modules
Requires-Python: >=3.9
License-File: LICENSE
Requires-Dist: huggingface_hub
Requires-Dist: lightrag-hku
Requires-Dist: mineru[core]
Requires-Dist: tqdm
Provides-Extra: image
Requires-Dist: Pillow>=10.0.0; extra == "image"
Provides-Extra: text
Requires-Dist: reportlab>=4.0.0; extra == "text"
Provides-Extra: office
Provides-Extra: all
Requires-Dist: Pillow>=10.0.0; extra == "all"
Requires-Dist: reportlab>=4.0.0; extra == "all"
Provides-Extra: markdown
Requires-Dist: markdown>=3.4.0; extra == "markdown"
Requires-Dist: weasyprint>=60.0; extra == "markdown"
Requires-Dist: pygments>=2.10.0; extra == "markdown"
Dynamic: author
Dynamic: classifier
Dynamic: description
Dynamic: description-content-type
Dynamic: home-page
Dynamic: license-file
Dynamic: project-url
Dynamic: provides-extra
Dynamic: requires-dist
Dynamic: requires-python
Dynamic: summary
